duplicates.py
romlm.py
tags.py
romlm-1.0.3.dist-info/licenses/LICENSE
romlm-1.0.3.dist-info/METADATA
romlm-1.0.3.dist-info/WHEEL
romlm-1.0.3.dist-info/entry_points.txt
romlm-1.0.3.dist-info/top_level.txt
romlm-1.0.3.dist-info/RECORD
