Metadata-Version: 2.4
Name: romlm
Version: 1.0.3
Summary: A ROM library management tool.
Author-email: Ilia Petrov-Komotskii <ilia@inkedkettle.art>
License: MIT
Project-URL: Repository, https://github.com/ManeFunction/romlm
Keywords: ROM,retro,retro-game,emulation,management,tools
Classifier: Programming Language :: Python :: 3
Classifier: License :: OSI Approved :: MIT License
Classifier: Operating System :: OS Independent
Requires-Python: >=3.6
License-File: LICENSE
Requires-Dist: py7zr==0.22.0
Requires-Dist: tqdm==4.67.1
Requires-Dist: colorama==0.4.6
Dynamic: license-file
